.gitignore
LICENSE
README.rst
setup.py
scTSS/__init__.py
scTSS/version.py
scTSS.egg-info/PKG-INFO
scTSS.egg-info/SOURCES.txt
scTSS.egg-info/dependency_links.txt
scTSS.egg-info/entry_points.txt
scTSS.egg-info/requires.txt
scTSS.egg-info/top_level.txt
scTSS/bin/__init__.py
scTSS/bin/count.py
scTSS/bin/plot.py
scTSS/bin/quant.py
scTSS/bin/scTSS_main.py
scTSS/utils/__init__.py
scTSS/utils/build_ref.py
scTSS/utils/get_count_no_novel.py
scTSS/utils/get_counts.py
scTSS/utils/get_inputfile_toBrie.py
test/32_4_feature.csv
test/Homo_sapiens.GRCh38.105.chr_test.gtf
test/cluster_toscTSS.tsv
test/logistic_36feature_model.sav
test/logistic_4feature_model.sav
test/train_fromSCAFE.csv
test/trian_ourself_dataset.csv