Metadata-Version: 2.1
Name: scTSS
Version: 0.0.3
Summary: scTSS: Detection and couting alternative TSS in single cells
Home-page: https://github.com/StatBiomed/scTSS
Author: ['scTSS Team']
Author-email: 
License: Apache-2.0
Keywords: Transcript Start Site,single-cell RNA-seq
Requires-Python: >=3.5
Provides-Extra: docs
License-File: LICENSE
